{"isAddBias":true,"inputs":[{"id":0,"x":0.1,"incoming":[]},{"id":1,"x":0.1,"incoming":[]},{"id":2,"x":0.1,"incoming":[]},{"id":3,"x":0.1,"incoming":[]},{"id":4,"x":0.1,"incoming":[]},{"id":5,"x":0.1,"incoming":[]},{"id":6,"x":0.1,"incoming":[]},{"id":7,"x":0.1,"incoming":[]},{"id":8,"x":0.1,"incoming":[]}],"hidden":[{"id":68,"x":0.29999998,"incoming":[{"fromId":4,"weight":1.4479551,"enabled":true},{"fromId":0,"weight":0.3223344,"enabled":true}]},{"id":31,"x":0.49999997,"incoming":[{"fromId":2,"weight":0.65676385,"enabled":true},{"fromId":0,"weight":-0.47772878,"enabled":true},{"fromId":4,"weight":0.033748027,"enabled":true},{"fromId":5,"weight":-0.57163304,"enabled":true}]},{"id":32,"x":0.49999997,"incoming":[{"fromId":4,"weight":-0.5678139,"enabled":true},{"fromId":0,"weight":-0.4761743,"enabled":true},{"fromId":1,"weight":0.39801726,"enabled":true},{"fromId":68,"weight":-0.3500058,"enabled":true}]},{"id":66,"x":0.49999997,"incoming":[{"fromId":3,"weight":0.34764436,"enabled":true},{"fromId":0,"weight":1.432951,"enabled":true}]}],"outputs":[{"id":9,"x":0.9,"incoming":[{"fromId":0,"weight":0.69158417,"enabled":true},{"fromId":1,"weight":1.9158096,"enabled":true},{"fromId":2,"weight":0.9155459,"enabled":false},{"fromId":3,"weight":-0.37825185,"enabled":true},{"fromId":4,"weight":1.3050834,"enabled":false},{"fromId":31,"weight":-0.76117927,"enabled":true},{"fromId":32,"weight":0.02324687,"enabled":true},{"fromId":8,"weight":-0.18861608,"enabled":true}]},{"id":10,"x":0.9,"incoming":[{"fromId":0,"weight":1.2566679,"enabled":true},{"fromId":1,"weight":-1.3239545,"enabled":true},{"fromId":2,"weight":0.99014395,"enabled":true},{"fromId":3,"weight":-1.0157592,"enabled":false},{"fromId":4,"weight":-0.60021305,"enabled":true},{"fromId":66,"weight":-0.8973,"enabled":true}]},{"id":11,"x":0.9,"incoming":[{"fromId":0,"weight":-0.18405387,"enabled":true},{"fromId":1,"weight":-1.5283114,"enabled":true},{"fromId":2,"weight":-0.2002582,"enabled":true},{"fromId":3,"weight":1.1365747,"enabled":true},{"fromId":4,"weight":-0.1573801,"enabled":true},{"fromId":8,"weight":-2.7423842,"enabled":true}]},{"id":12,"x":0.9,"incoming":[{"fromId":0,"weight":0.591182,"enabled":true},{"fromId":1,"weight":-0.3753128,"enabled":true},{"fromId":2,"weight":0.7530101,"enabled":true},{"fromId":3,"weight":-1.169985,"enabled":true},{"fromId":4,"weight":-1.4482647,"enabled":true}]}]}